{
  "id" : "https://Melodiedoumy.github.io/Test-DiamondSutra/manifests/collection.json",
  "label" : {
    "en" : [ "All manifests loaded in Melodiedoumy/Test-DiamondSutra project" ]
  },
  "type" : "Collection",
  "@context" : "http://iiif.io/api/presentation/3/context.json",
  "items" : [ {
    "@type" : "sc:Manifest",
    "@id" : "https://Melodiedoumy.github.io/Test-DiamondSutra/manifests/Diamondsutramanifest2.json",
    "label" : "Printed copy of the Diamond Sutra (Skt. Vajracchedikā Prajñāpāramitā Sūtra)"
  } ]
}